cryptoguardianTeste/__init__.py
cryptoguardianTeste/teste.py
cryptoguardianTeste-0.0.1.dist-info/LICENSE
cryptoguardianTeste-0.0.1.dist-info/METADATA
cryptoguardianTeste-0.0.1.dist-info/WHEEL
cryptoguardianTeste-0.0.1.dist-info/top_level.txt
cryptoguardianTeste-0.0.1.dist-info/RECORD
